MANIFEST.in
README.md
setup.cfg
setup.py
bench/__init__.py
bench/fftconv.py
bench/gen.py
bench/lowpass.py
bench/resample.py
docs/julius/bands.html
docs/julius/core.html
docs/julius/fftconv.html
docs/julius/filters.html
docs/julius/index.html
docs/julius/lowpass.html
docs/julius/resample.html
docs/julius/utils.html
julius/__init__.py
julius/bands.py
julius/core.py
julius/fftconv.py
julius/filters.py
julius/lowpass.py
julius/py.typed
julius/resample.py
julius/utils.py
julius.egg-info/PKG-INFO
julius.egg-info/SOURCES.txt
julius.egg-info/dependency_links.txt
julius.egg-info/requires.txt
julius.egg-info/top_level.txt
tests/__init__.py
tests/test_bands.py
tests/test_doc.py
tests/test_fftconv.py
tests/test_filters.py
tests/test_lowpass.py
tests/test_resample.py