Metadata-Version: 2.1
Name: julius
Version: 0.2.6
Summary: Nice DSP sweets: resampling, FFT Convolutions. All with PyTorch, differentiable and with CUDA support.
Home-page: https://github.com/adefossez/julius
Author: Alexandre Défossez
Author-email: alexandre.defossez@gmail.com
License: MIT License
Platform: UNKNOWN
Classifier: License :: OSI Approved :: MIT License
Classifier: Topic :: Multimedia :: Sound/Audio
Classifier: Topic :: Scientific/Engineering
Requires-Python: >=3.6.0
Provides-Extra: dev
